creta
